aws_ecs_exec/__init__.py
aws_ecs_exec/cli.py
aws_ecs_exec/colors.py
aws_ecs_exec/exceptions.py
aws_ecs_exec/utils.py
aws_ecs_exec/widgets.py
aws_ecs_exec-0.1.1.dist-info/METADATA
aws_ecs_exec-0.1.1.dist-info/WHEEL
aws_ecs_exec-0.1.1.dist-info/entry_points.txt
aws_ecs_exec-0.1.1.dist-info/RECORD
