Metadata-Version: 2.1
Name: aws-ecs-exec
Version: 0.1.1
Summary: A cli tool to conveniently execute commands in AWS ECS Tasks
License: MIT
Author: Nat Gordon
Author-email: nat@nattyg93.com.au
Requires-Python: >=3.10,<4.0
Classifier: License :: OSI Approved :: MIT License
Classifier: Programming Language :: Python :: 3
Classifier: Programming Language :: Python :: 3.10
Classifier: Programming Language :: Python :: 3.11
Requires-Dist: boto3 (>=1.26,<2.0)
Requires-Dist: botocore (>=1.26,<2.0)
Requires-Dist: readchar (>=4.0.5,<5.0.0)
Requires-Dist: termcolor (>=2.3.0,<3.0.0)
